{
	"$schema": "http://schema.management.azure.com/schemas/2015-01-01/deploymentTemplate.json#",
	"contentVersion": "1.0.0.0",
	"parameters": {
		"factoryName": {
			"type": "string",
			"metadata": "Data Factory name",
			"defaultValue": "financedevdemo1"
		},
		"is_adls_accountKey": {
			"type": "secureString",
			"metadata": "Secure string for 'accountKey' of 'is_adls'"
		},
		"is_blb_connectionString": {
			"type": "secureString",
			"metadata": "Secure string for 'connectionString' of 'is_blb'"
		},
		"is_adls_properties_typeProperties_url": {
			"type": "string",
			"defaultValue": "https://adlsfinancestaggingdev.dfs.core.windows.net/"
		}
	},
	"variables": {
		"factoryId": "[concat('Microsoft.DataFactory/factories/', parameters('factoryName'))]"
	},
	"resources": [
		{
			"name": "[concat(parameters('factoryName'), '/is_adls')]",
			"type": "Microsoft.DataFactory/factories/linkedServices",
			"apiVersion": "2018-06-01",
			"properties": {
				"annotations": [],
				"type": "AzureBlobFS",
				"typeProperties": {
					"url": "[parameters('is_adls_properties_typeProperties_url')]",
					"accountKey": {
						"type": "SecureString",
						"value": "[parameters('is_adls_accountKey')]"
					}
				}
			},
			"dependsOn": []
		},
		{
			"name": "[concat(parameters('factoryName'), '/is_blb')]",
			"type": "Microsoft.DataFactory/factories/linkedServices",
			"apiVersion": "2018-06-01",
			"properties": {
				"annotations": [],
				"type": "AzureBlobStorage",
				"typeProperties": {
					"connectionString": "[parameters('is_blb_connectionString')]"
				}
			},
			"dependsOn": []
		},
		{
			"name": "[concat(parameters('factoryName'), '/dp_helper_sink_blb_folder_replicate')]",
			"type": "Microsoft.DataFactory/factories/datasets",
			"apiVersion": "2018-06-01",
			"properties": {
				"linkedServiceName": {
					"referenceName": "is_blb",
					"type": "LinkedServiceReference"
				},
				"parameters": {
					"destinationFolder": {
						"type": "string",
						"defaultValue": "Exer/Les1_1"
					}
				},
				"folder": {
					"name": "HELPER"
				},
				"annotations": [],
				"type": "DelimitedText",
				"typeProperties": {
					"location": {
						"type": "AzureBlobStorageLocation",
						"folderPath": {
							"value": "@dataset().destinationFolder",
							"type": "Expression"
						},
						"container": "raw"
					},
					"columnDelimiter": ",",
					"escapeChar": "\\",
					"firstRowAsHeader": true,
					"quoteChar": "\""
				},
				"schema": []
			},
			"dependsOn": [
				"[concat(variables('factoryId'), '/linkedServices/is_blb')]"
			]
		},
		{
			"name": "[concat(parameters('factoryName'), '/dp_helper_src_blb_folder_replicate')]",
			"type": "Microsoft.DataFactory/factories/datasets",
			"apiVersion": "2018-06-01",
			"properties": {
				"linkedServiceName": {
					"referenceName": "is_blb",
					"type": "LinkedServiceReference"
				},
				"parameters": {
					"sourceFolder": {
						"type": "String",
						"defaultValue": "Exer/Ex2"
					}
				},
				"folder": {
					"name": "HELPER"
				},
				"annotations": [],
				"type": "DelimitedText",
				"typeProperties": {
					"location": {
						"type": "AzureBlobStorageLocation",
						"folderPath": {
							"value": "@dataset().sourceFolder",
							"type": "Expression"
						},
						"container": "raw"
					},
					"columnDelimiter": ",",
					"escapeChar": "\\",
					"firstRowAsHeader": true,
					"quoteChar": "\""
				},
				"schema": []
			},
			"dependsOn": [
				"[concat(variables('factoryId'), '/linkedServices/is_blb')]"
			]
		},
		{
			"name": "[concat(parameters('factoryName'), '/ds_ex1_sink_adls_csv')]",
			"type": "Microsoft.DataFactory/factories/datasets",
			"apiVersion": "2018-06-01",
			"properties": {
				"linkedServiceName": {
					"referenceName": "is_adls",
					"type": "LinkedServiceReference"
				},
				"folder": {
					"name": "Target"
				},
				"annotations": [],
				"type": "DelimitedText",
				"typeProperties": {
					"location": {
						"type": "AzureBlobFSLocation",
						"folderPath": {
							"value": "@concat('Exer/Ex1/',formatDateTime(utcNow(), 'MMddyyyyThhmmss'),'UTC')",
							"type": "Expression"
						},
						"fileSystem": "bronze"
					},
					"columnDelimiter": ",",
					"escapeChar": "\\",
					"firstRowAsHeader": true,
					"quoteChar": "\""
				},
				"schema": [
					{
						"name": "Session_Connection_Time",
						"type": "String"
					},
					{
						"name": "Bytes Transferred",
						"type": "String"
					},
					{
						"name": "Kali_Trace_Used",
						"type": "String"
					},
					{
						"name": "Servers_Corrupted",
						"type": "String"
					},
					{
						"name": "Pages_Corrupted",
						"type": "String"
					},
					{
						"name": "Location",
						"type": "String"
					},
					{
						"name": "WPM_Typing_Speed",
						"type": "String"
					},
					{
						"name": "hack",
						"type": "String"
					}
				]
			},
			"dependsOn": [
				"[concat(variables('factoryId'), '/linkedServices/is_adls')]"
			]
		},
		{
			"name": "[concat(parameters('factoryName'), '/ds_ex1_src_blb_csv')]",
			"type": "Microsoft.DataFactory/factories/datasets",
			"apiVersion": "2018-06-01",
			"properties": {
				"linkedServiceName": {
					"referenceName": "is_blb",
					"type": "LinkedServiceReference"
				},
				"folder": {
					"name": "Source"
				},
				"annotations": [],
				"type": "DelimitedText",
				"typeProperties": {
					"location": {
						"type": "AzureBlobStorageLocation",
						"fileName": "hack_data.csv",
						"folderPath": "Exer/Ex1",
						"container": "raw"
					},
					"columnDelimiter": ",",
					"escapeChar": "\\",
					"firstRowAsHeader": true,
					"quoteChar": "\""
				},
				"schema": [
					{
						"name": "Session_Connection_Time",
						"type": "String"
					},
					{
						"name": "Bytes Transferred",
						"type": "String"
					},
					{
						"name": "Kali_Trace_Used",
						"type": "String"
					},
					{
						"name": "Servers_Corrupted",
						"type": "String"
					},
					{
						"name": "Pages_Corrupted",
						"type": "String"
					},
					{
						"name": "Location",
						"type": "String"
					},
					{
						"name": "WPM_Typing_Speed",
						"type": "String"
					},
					{
						"name": "hack",
						"type": "String"
					}
				]
			},
			"dependsOn": [
				"[concat(variables('factoryId'), '/linkedServices/is_blb')]"
			]
		},
		{
			"name": "[concat(parameters('factoryName'), '/ds_ex2_sink_adls_folderHier_mul_files')]",
			"type": "Microsoft.DataFactory/factories/datasets",
			"apiVersion": "2018-06-01",
			"properties": {
				"linkedServiceName": {
					"referenceName": "is_adls",
					"type": "LinkedServiceReference"
				},
				"folder": {
					"name": "Target"
				},
				"annotations": [],
				"type": "DelimitedText",
				"typeProperties": {
					"location": {
						"type": "AzureBlobFSLocation",
						"folderPath": {
							"value": "@concat('Exer/Ex2/',formatDateTime(utcNow(), 'MMddyyyyThhmmss'),'UTC')",
							"type": "Expression"
						},
						"fileSystem": "bronze"
					},
					"columnDelimiter": ",",
					"escapeChar": "\\",
					"firstRowAsHeader": true,
					"quoteChar": "\""
				},
				"schema": [
					{
						"name": "Session_Connection_Time",
						"type": "String"
					},
					{
						"name": "Bytes Transferred",
						"type": "String"
					},
					{
						"name": "Kali_Trace_Used",
						"type": "String"
					},
					{
						"name": "Servers_Corrupted",
						"type": "String"
					},
					{
						"name": "Pages_Corrupted",
						"type": "String"
					},
					{
						"name": "Location",
						"type": "String"
					},
					{
						"name": "WPM_Typing_Speed",
						"type": "String"
					},
					{
						"name": "hack",
						"type": "String"
					}
				]
			},
			"dependsOn": [
				"[concat(variables('factoryId'), '/linkedServices/is_adls')]"
			]
		},
		{
			"name": "[concat(parameters('factoryName'), '/ds_ex2_src_blb_folderHier_mul_files')]",
			"type": "Microsoft.DataFactory/factories/datasets",
			"apiVersion": "2018-06-01",
			"properties": {
				"linkedServiceName": {
					"referenceName": "is_blb",
					"type": "LinkedServiceReference"
				},
				"folder": {
					"name": "Source"
				},
				"annotations": [],
				"type": "DelimitedText",
				"typeProperties": {
					"location": {
						"type": "AzureBlobStorageLocation",
						"folderPath": "Exer/Ex2",
						"container": "raw"
					},
					"columnDelimiter": ",",
					"escapeChar": "\\",
					"firstRowAsHeader": true,
					"quoteChar": "\""
				},
				"schema": [
					{
						"name": "Session_Connection_Time",
						"type": "String"
					},
					{
						"name": "Bytes Transferred",
						"type": "String"
					},
					{
						"name": "Kali_Trace_Used",
						"type": "String"
					},
					{
						"name": "Servers_Corrupted",
						"type": "String"
					},
					{
						"name": "Pages_Corrupted",
						"type": "String"
					},
					{
						"name": "Location",
						"type": "String"
					},
					{
						"name": "WPM_Typing_Speed",
						"type": "String"
					},
					{
						"name": "hack",
						"type": "String"
					}
				]
			},
			"dependsOn": [
				"[concat(variables('factoryId'), '/linkedServices/is_blb')]"
			]
		},
		{
			"name": "[concat(parameters('factoryName'), '/ds_les2_1_sink_adls_json')]",
			"type": "Microsoft.DataFactory/factories/datasets",
			"apiVersion": "2018-06-01",
			"properties": {
				"linkedServiceName": {
					"referenceName": "is_adls",
					"type": "LinkedServiceReference"
				},
				"folder": {
					"name": "Target"
				},
				"annotations": [],
				"type": "Json",
				"typeProperties": {
					"location": {
						"type": "AzureBlobFSLocation",
						"fileName": "hack.json",
						"folderPath": {
							"value": "@concat('Exer/Les2_1/',formatDateTime(utcNow(), 'MMddyyyyThhmmss'),'UTC')",
							"type": "Expression"
						},
						"fileSystem": "bronze"
					}
				},
				"schema": {}
			},
			"dependsOn": [
				"[concat(variables('factoryId'), '/linkedServices/is_adls')]"
			]
		},
		{
			"name": "[concat(parameters('factoryName'), '/ds_les2_1_src_blb_csv')]",
			"type": "Microsoft.DataFactory/factories/datasets",
			"apiVersion": "2018-06-01",
			"properties": {
				"linkedServiceName": {
					"referenceName": "is_blb",
					"type": "LinkedServiceReference"
				},
				"folder": {
					"name": "Source"
				},
				"annotations": [],
				"type": "DelimitedText",
				"typeProperties": {
					"location": {
						"type": "AzureBlobStorageLocation",
						"fileName": "hack_data.csv",
						"folderPath": "Exer/Les2_1",
						"container": "raw"
					},
					"columnDelimiter": ",",
					"escapeChar": "\\",
					"firstRowAsHeader": true,
					"quoteChar": "\""
				},
				"schema": [
					{
						"name": "Session_Connection_Time",
						"type": "String"
					},
					{
						"name": "Bytes Transferred",
						"type": "String"
					},
					{
						"name": "Kali_Trace_Used",
						"type": "String"
					},
					{
						"name": "Servers_Corrupted",
						"type": "String"
					},
					{
						"name": "Pages_Corrupted",
						"type": "String"
					},
					{
						"name": "Location",
						"type": "String"
					},
					{
						"name": "WPM_Typing_Speed",
						"type": "String"
					},
					{
						"name": "hack",
						"type": "String"
					}
				]
			},
			"dependsOn": [
				"[concat(variables('factoryId'), '/linkedServices/is_blb')]"
			]
		},
		{
			"name": "[concat(parameters('factoryName'), '/pip_ex1_copy_csv')]",
			"type": "Microsoft.DataFactory/factories/pipelines",
			"apiVersion": "2018-06-01",
			"properties": {
				"activities": [
					{
						"name": "Copy data1",
						"type": "Copy",
						"dependsOn": [],
						"policy": {
							"timeout": "0.12:00:00",
							"retry": 0,
							"retryIntervalInSeconds": 30,
							"secureOutput": false,
							"secureInput": false
						},
						"userProperties": [],
						"typeProperties": {
							"source": {
								"type": "DelimitedTextSource",
								"storeSettings": {
									"type": "AzureBlobStorageReadSettings",
									"recursive": true,
									"enablePartitionDiscovery": false
								},
								"formatSettings": {
									"type": "DelimitedTextReadSettings"
								}
							},
							"sink": {
								"type": "DelimitedTextSink",
								"storeSettings": {
									"type": "AzureBlobFSWriteSettings"
								},
								"formatSettings": {
									"type": "DelimitedTextWriteSettings",
									"quoteAllText": true,
									"fileExtension": ".txt"
								}
							},
							"enableStaging": false,
							"translator": {
								"type": "TabularTranslator",
								"typeConversion": true,
								"typeConversionSettings": {
									"allowDataTruncation": true,
									"treatBooleanAsNumber": false
								}
							}
						},
						"inputs": [
							{
								"referenceName": "ds_ex1_src_blb_csv",
								"type": "DatasetReference",
								"parameters": {}
							}
						],
						"outputs": [
							{
								"referenceName": "ds_ex1_sink_adls_csv",
								"type": "DatasetReference",
								"parameters": {}
							}
						]
					}
				],
				"policy": {
					"elapsedTimeMetric": {}
				},
				"annotations": []
			},
			"dependsOn": [
				"[concat(variables('factoryId'), '/datasets/ds_ex1_src_blb_csv')]",
				"[concat(variables('factoryId'), '/datasets/ds_ex1_sink_adls_csv')]"
			]
		},
		{
			"name": "[concat(parameters('factoryName'), '/pip_ex2_1_copy_folderHier_mul_files')]",
			"type": "Microsoft.DataFactory/factories/pipelines",
			"apiVersion": "2018-06-01",
			"properties": {
				"activities": [
					{
						"name": "Copy data1",
						"type": "Copy",
						"dependsOn": [],
						"policy": {
							"timeout": "0.12:00:00",
							"retry": 0,
							"retryIntervalInSeconds": 30,
							"secureOutput": false,
							"secureInput": false
						},
						"userProperties": [],
						"typeProperties": {
							"source": {
								"type": "DelimitedTextSource",
								"storeSettings": {
									"type": "AzureBlobStorageReadSettings",
									"recursive": true,
									"wildcardFileName": "*",
									"enablePartitionDiscovery": false
								},
								"formatSettings": {
									"type": "DelimitedTextReadSettings"
								}
							},
							"sink": {
								"type": "DelimitedTextSink",
								"storeSettings": {
									"type": "AzureBlobFSWriteSettings",
									"copyBehavior": "PreserveHierarchy"
								},
								"formatSettings": {
									"type": "DelimitedTextWriteSettings",
									"quoteAllText": true,
									"fileExtension": ".txt"
								}
							},
							"enableStaging": false,
							"translator": {
								"type": "TabularTranslator",
								"typeConversion": true,
								"typeConversionSettings": {
									"allowDataTruncation": true,
									"treatBooleanAsNumber": false
								}
							}
						},
						"inputs": [
							{
								"referenceName": "ds_ex2_src_blb_folderHier_mul_files",
								"type": "DatasetReference",
								"parameters": {}
							}
						],
						"outputs": [
							{
								"referenceName": "ds_ex2_sink_adls_folderHier_mul_files",
								"type": "DatasetReference",
								"parameters": {}
							}
						]
					}
				],
				"policy": {
					"elapsedTimeMetric": {}
				},
				"annotations": []
			},
			"dependsOn": [
				"[concat(variables('factoryId'), '/datasets/ds_ex2_src_blb_folderHier_mul_files')]",
				"[concat(variables('factoryId'), '/datasets/ds_ex2_sink_adls_folderHier_mul_files')]"
			]
		},
		{
			"name": "[concat(parameters('factoryName'), '/pip_ex2_2_copy_folderHier_mul_files')]",
			"type": "Microsoft.DataFactory/factories/pipelines",
			"apiVersion": "2018-06-01",
			"properties": {
				"activities": [
					{
						"name": "Copy data1",
						"type": "Copy",
						"dependsOn": [],
						"policy": {
							"timeout": "0.12:00:00",
							"retry": 0,
							"retryIntervalInSeconds": 30,
							"secureOutput": false,
							"secureInput": false
						},
						"userProperties": [],
						"typeProperties": {
							"source": {
								"type": "DelimitedTextSource",
								"storeSettings": {
									"type": "AzureBlobStorageReadSettings",
									"recursive": true,
									"wildcardFolderPath": "Exer/Ex2/csv",
									"wildcardFileName": "*",
									"enablePartitionDiscovery": false
								},
								"formatSettings": {
									"type": "DelimitedTextReadSettings"
								}
							},
							"sink": {
								"type": "DelimitedTextSink",
								"storeSettings": {
									"type": "AzureBlobFSWriteSettings",
									"copyBehavior": "PreserveHierarchy"
								},
								"formatSettings": {
									"type": "DelimitedTextWriteSettings",
									"quoteAllText": true,
									"fileExtension": ".txt"
								}
							},
							"enableStaging": false,
							"translator": {
								"type": "TabularTranslator",
								"typeConversion": true,
								"typeConversionSettings": {
									"allowDataTruncation": true,
									"treatBooleanAsNumber": false
								}
							}
						},
						"inputs": [
							{
								"referenceName": "ds_ex2_src_blb_folderHier_mul_files",
								"type": "DatasetReference",
								"parameters": {}
							}
						],
						"outputs": [
							{
								"referenceName": "ds_ex2_sink_adls_folderHier_mul_files",
								"type": "DatasetReference",
								"parameters": {}
							}
						]
					}
				],
				"policy": {
					"elapsedTimeMetric": {}
				},
				"annotations": []
			},
			"dependsOn": [
				"[concat(variables('factoryId'), '/datasets/ds_ex2_src_blb_folderHier_mul_files')]",
				"[concat(variables('factoryId'), '/datasets/ds_ex2_sink_adls_folderHier_mul_files')]"
			]
		},
		{
			"name": "[concat(parameters('factoryName'), '/pip_helper_blb_srcfolder_replicate')]",
			"type": "Microsoft.DataFactory/factories/pipelines",
			"apiVersion": "2018-06-01",
			"properties": {
				"activities": [
					{
						"name": "Copy data1",
						"type": "Copy",
						"dependsOn": [],
						"policy": {
							"timeout": "0.12:00:00",
							"retry": 0,
							"retryIntervalInSeconds": 30,
							"secureOutput": false,
							"secureInput": false
						},
						"userProperties": [],
						"typeProperties": {
							"source": {
								"type": "DelimitedTextSource",
								"storeSettings": {
									"type": "AzureBlobStorageReadSettings",
									"recursive": true,
									"wildcardFileName": "*",
									"enablePartitionDiscovery": false
								},
								"formatSettings": {
									"type": "DelimitedTextReadSettings"
								}
							},
							"sink": {
								"type": "DelimitedTextSink",
								"storeSettings": {
									"type": "AzureBlobStorageWriteSettings",
									"copyBehavior": "PreserveHierarchy"
								},
								"formatSettings": {
									"type": "DelimitedTextWriteSettings",
									"quoteAllText": true,
									"fileExtension": ".txt"
								}
							},
							"enableStaging": false,
							"translator": {
								"type": "TabularTranslator",
								"typeConversion": true,
								"typeConversionSettings": {
									"allowDataTruncation": true,
									"treatBooleanAsNumber": false
								}
							}
						},
						"inputs": [
							{
								"referenceName": "dp_helper_src_blb_folder_replicate",
								"type": "DatasetReference",
								"parameters": {
									"sourceFolder": "Exer/Les2_1"
								}
							}
						],
						"outputs": [
							{
								"referenceName": "dp_helper_sink_blb_folder_replicate",
								"type": "DatasetReference",
								"parameters": {
									"destinationFolder": "Exer/Backup/Les2_1"
								}
							}
						]
					}
				],
				"policy": {
					"elapsedTimeMetric": {}
				},
				"folder": {
					"name": "HELPER"
				},
				"annotations": []
			},
			"dependsOn": [
				"[concat(variables('factoryId'), '/datasets/dp_helper_src_blb_folder_replicate')]",
				"[concat(variables('factoryId'), '/datasets/dp_helper_sink_blb_folder_replicate')]"
			]
		},
		{
			"name": "[concat(parameters('factoryName'), '/pip_les2_1_copy_del_csv')]",
			"type": "Microsoft.DataFactory/factories/pipelines",
			"apiVersion": "2018-06-01",
			"properties": {
				"activities": [
					{
						"name": "Copy data1",
						"type": "Copy",
						"dependsOn": [],
						"policy": {
							"timeout": "0.12:00:00",
							"retry": 0,
							"retryIntervalInSeconds": 30,
							"secureOutput": false,
							"secureInput": false
						},
						"userProperties": [],
						"typeProperties": {
							"source": {
								"type": "DelimitedTextSource",
								"storeSettings": {
									"type": "AzureBlobStorageReadSettings",
									"recursive": true,
									"enablePartitionDiscovery": false
								},
								"formatSettings": {
									"type": "DelimitedTextReadSettings"
								}
							},
							"sink": {
								"type": "JsonSink",
								"storeSettings": {
									"type": "AzureBlobFSWriteSettings",
									"copyBehavior": "PreserveHierarchy"
								},
								"formatSettings": {
									"type": "JsonWriteSettings"
								}
							},
							"enableStaging": false
						},
						"inputs": [
							{
								"referenceName": "ds_les2_1_src_blb_csv",
								"type": "DatasetReference",
								"parameters": {}
							}
						],
						"outputs": [
							{
								"referenceName": "ds_les2_1_sink_adls_json",
								"type": "DatasetReference",
								"parameters": {}
							}
						]
					},
					{
						"name": "Delete1",
						"type": "Delete",
						"dependsOn": [
							{
								"activity": "Copy data1",
								"dependencyConditions": [
									"Succeeded"
								]
							}
						],
						"policy": {
							"timeout": "0.12:00:00",
							"retry": 0,
							"retryIntervalInSeconds": 30,
							"secureOutput": false,
							"secureInput": false
						},
						"userProperties": [],
						"typeProperties": {
							"dataset": {
								"referenceName": "ds_les2_1_src_blb_csv",
								"type": "DatasetReference",
								"parameters": {}
							},
							"enableLogging": false,
							"storeSettings": {
								"type": "AzureBlobStorageReadSettings",
								"recursive": true,
								"enablePartitionDiscovery": false
							}
						}
					}
				],
				"policy": {
					"elapsedTimeMetric": {}
				},
				"annotations": []
			},
			"dependsOn": [
				"[concat(variables('factoryId'), '/datasets/ds_les2_1_src_blb_csv')]",
				"[concat(variables('factoryId'), '/datasets/ds_les2_1_sink_adls_json')]"
			]
		},
		{
			"name": "[concat(parameters('factoryName'), '/pip_les2_2_copy_del_folderHier_mul_files')]",
			"type": "Microsoft.DataFactory/factories/pipelines",
			"apiVersion": "2018-06-01",
			"properties": {
				"activities": [
					{
						"name": "Copy data1",
						"type": "Copy",
						"dependsOn": [],
						"policy": {
							"timeout": "0.12:00:00",
							"retry": 0,
							"retryIntervalInSeconds": 30,
							"secureOutput": false,
							"secureInput": false
						},
						"userProperties": [],
						"typeProperties": {
							"source": {
								"type": "DelimitedTextSource",
								"storeSettings": {
									"type": "AzureBlobStorageReadSettings",
									"recursive": true,
									"enablePartitionDiscovery": false
								},
								"formatSettings": {
									"type": "DelimitedTextReadSettings"
								}
							},
							"sink": {
								"type": "JsonSink",
								"storeSettings": {
									"type": "AzureBlobFSWriteSettings",
									"copyBehavior": "PreserveHierarchy"
								},
								"formatSettings": {
									"type": "JsonWriteSettings"
								}
							},
							"enableStaging": false
						},
						"inputs": [
							{
								"referenceName": "ds_les2_1_src_blb_csv",
								"type": "DatasetReference",
								"parameters": {}
							}
						],
						"outputs": [
							{
								"referenceName": "ds_les2_1_sink_adls_json",
								"type": "DatasetReference",
								"parameters": {}
							}
						]
					},
					{
						"name": "Delete1",
						"type": "Delete",
						"dependsOn": [
							{
								"activity": "Copy data1",
								"dependencyConditions": [
									"Succeeded"
								]
							}
						],
						"policy": {
							"timeout": "0.12:00:00",
							"retry": 0,
							"retryIntervalInSeconds": 30,
							"secureOutput": false,
							"secureInput": false
						},
						"userProperties": [],
						"typeProperties": {
							"dataset": {
								"referenceName": "ds_les2_1_src_blb_csv",
								"type": "DatasetReference",
								"parameters": {}
							},
							"enableLogging": false,
							"storeSettings": {
								"type": "AzureBlobStorageReadSettings",
								"recursive": true,
								"enablePartitionDiscovery": false
							}
						}
					}
				],
				"policy": {
					"elapsedTimeMetric": {}
				},
				"annotations": []
			},
			"dependsOn": [
				"[concat(variables('factoryId'), '/datasets/ds_les2_1_src_blb_csv')]",
				"[concat(variables('factoryId'), '/datasets/ds_les2_1_sink_adls_json')]"
			]
		}
	]
}